incytr_viz/__init__.py
incytr_viz/__main__.py
incytr_viz/app.py
incytr_viz/components.py
incytr_viz/dtypes.py
incytr_viz/util.py
incytr_viz/wsgi_posix.py
incytr_viz/wsgi_windows.py
incytr_viz/assets/click.gif
incytr_viz/assets/color.gif
incytr_viz/assets/filter.gif
incytr_viz/assets/help.md
incytr_viz/assets/incytr.css
incytr_viz/assets/river.gif
incytr_viz/assets/umap.gif
incytr_viz-0.0.1.dist-info/LICENSE
incytr_viz-0.0.1.dist-info/METADATA
incytr_viz-0.0.1.dist-info/NOTICE
incytr_viz-0.0.1.dist-info/WHEEL
incytr_viz-0.0.1.dist-info/entry_points.txt
incytr_viz-0.0.1.dist-info/top_level.txt
incytr_viz-0.0.1.dist-info/RECORD
