Metadata-Version: 2.2
Name: incytr_viz
Version: 0.0.1
Summary: A browser-based tool to visualize and interact with signaling pathways returned InCytr.
Author-email: Ian Cossentino <ian.cossentino@cellsignal.com>
Project-URL: Source code, https://github.com/cellsignal/incytr-viz
Classifier: Programming Language :: Python :: 3
Classifier: License :: OSI Approved :: MIT License
Classifier: Operating System :: OS Independent
Requires-Python: >=3.10
License-File: LICENSE
License-File: NOTICE
Requires-Dist: dash>=2.18.2
Requires-Dist: dash_cytoscape==0.3.0
Requires-Dist: dash-bootstrap-components==1.6.0
Requires-Dist: pandas
Requires-Dist: plotly>=5.24.1
Requires-Dist: matplotlib
Requires-Dist: gunicorn>=23.0.0; sys_platform != "win32"
Requires-Dist: tqdm
Requires-Dist: waitress>=3.0.2; sys_platform == "win32"
Provides-Extra: test
Requires-Dist: pytest>=7.3.1; extra == "test"
Requires-Dist: pytest-cov>=4.0.0; extra == "test"
Requires-Dist: black>=23.1.0; extra == "test"
Requires-Dist: flake8>=6.0.0; extra == "test"
Requires-Dist: pytest-mock; extra == "test"
